outlierx/__init__.py
outlierx/core.py
outlierx/iqr.py
outlierx/quantile.py
outlierx/zscore.py
outlierx-0.1.0.dist-info/METADATA
outlierx-0.1.0.dist-info/WHEEL
outlierx-0.1.0.dist-info/top_level.txt
outlierx-0.1.0.dist-info/RECORD
